agentic_codebase_navigator-1.2.0.dist-info/licenses/LICENSE
rlm/__init__.py
rlm/__main__.py
rlm/_meta.py
rlm/cli.py
rlm/adapters/__init__.py
rlm/adapters/base.py
rlm/adapters/sdk_boundaries.py
rlm/adapters/broker/__init__.py
rlm/adapters/broker/tcp.py
rlm/adapters/environments/__init__.py
rlm/adapters/environments/docker.py
rlm/adapters/environments/local.py
rlm/adapters/environments/modal.py
rlm/adapters/environments/prime.py
rlm/adapters/llm/__init__.py
rlm/adapters/llm/anthropic.py
rlm/adapters/llm/azure_openai.py
rlm/adapters/llm/gemini.py
rlm/adapters/llm/litellm.py
rlm/adapters/llm/mock.py
rlm/adapters/llm/openai.py
rlm/adapters/llm/portkey.py
rlm/adapters/llm/provider_base.py
rlm/adapters/logger/__init__.py
rlm/adapters/logger/console.py
rlm/adapters/logger/jsonl.py
rlm/adapters/logger/noop.py
rlm/adapters/policies/__init__.py
rlm/adapters/policies/compression.py
rlm/adapters/policies/nested.py
rlm/adapters/policies/stopping.py
rlm/adapters/tools/__init__.py
rlm/adapters/tools/native.py
rlm/adapters/tools/pydantic_output.py
rlm/adapters/tools/registry.py
rlm/api/__init__.py
rlm/api/factory.py
rlm/api/registries.py
rlm/api/rlm.py
rlm/application/__init__.py
rlm/application/config.py
rlm/application/use_cases/__init__.py
rlm/application/use_cases/run_completion.py
rlm/codebase/__init__.py
rlm/domain/__init__.py
rlm/domain/agent_ports.py
rlm/domain/errors.py
rlm/domain/ports.py
rlm/domain/result.py
rlm/domain/types.py
rlm/domain/models/__init__.py
rlm/domain/models/completion.py
rlm/domain/models/iteration.py
rlm/domain/models/json_schema_mapper.py
rlm/domain/models/llm_request.py
rlm/domain/models/model_spec.py
rlm/domain/models/orchestration_types.py
rlm/domain/models/query_metadata.py
rlm/domain/models/repl.py
rlm/domain/models/result.py
rlm/domain/models/run_metadata.py
rlm/domain/models/safe_accessor.py
rlm/domain/models/serialization.py
rlm/domain/models/state_machine.py
rlm/domain/models/type_mapping.py
rlm/domain/models/usage.py
rlm/domain/models/validation.py
rlm/domain/policies/__init__.py
agentic_codebase_navigator-1.2.0.dist-info/METADATA
agentic_codebase_navigator-1.2.0.dist-info/WHEEL
agentic_codebase_navigator-1.2.0.dist-info/entry_points.txt
agentic_codebase_navigator-1.2.0.dist-info/top_level.txt
agentic_codebase_navigator-1.2.0.dist-info/RECORD
