Metadata-Version: 2.4
Name: agentic-codebase-navigator
Version: 1.2.0
Summary: Agentic codebase navigator built on Recursive Language Model (RLM) patterns.
Author: Luiz Frias
Maintainer: Luiz Frias
License: MIT License
Project-URL: Repository, https://github.com/Luiz-Frias/agentic-codebase-navigator
Project-URL: Issues, https://github.com/Luiz-Frias/agentic-codebase-navigator/issues
Project-URL: Changelog, https://github.com/Luiz-Frias/agentic-codebase-navigator/blob/main/CHANGELOG.md
Project-URL: Documentation, https://github.com/Luiz-Frias/agentic-codebase-navigator#readme
Keywords: rlm,agentic,llm,code-execution,codebase,recursive-language-models
Classifier: Development Status :: 5 - Production/Stable
Classifier: Intended Audience :: Developers
Classifier: License :: OSI Approved :: MIT License
Classifier: Operating System :: OS Independent
Classifier: Programming Language :: Python :: 3
Classifier: Programming Language :: Python :: 3.12
Classifier: Topic :: Scientific/Engineering :: Artificial Intelligence
Classifier: Topic :: Software Development :: Libraries :: Python Modules
Classifier: Typing :: Typed
Requires-Python: >=3.12
License-File: LICENSE
Requires-Dist: openai>=2.14.0
Requires-Dist: loguru>=0.7.0
Provides-Extra: llm-openai
Requires-Dist: openai>=2.14.0; extra == "llm-openai"
Requires-Dist: tiktoken>=0.7.0; extra == "llm-openai"
Provides-Extra: llm-anthropic
Requires-Dist: anthropic>=0.75.0; extra == "llm-anthropic"
Provides-Extra: llm-gemini
Requires-Dist: google-genai>=1.56.0; extra == "llm-gemini"
Provides-Extra: llm-portkey
Requires-Dist: portkey-ai>=2.1.0; extra == "llm-portkey"
Provides-Extra: llm-litellm
Requires-Dist: litellm>=1.0.0; extra == "llm-litellm"
Provides-Extra: llm-azure-openai
Requires-Dist: openai>=2.14.0; extra == "llm-azure-openai"
Requires-Dist: tiktoken>=0.10.0; extra == "llm-azure-openai"
Provides-Extra: env-modal
Requires-Dist: modal>=0.73.0; extra == "env-modal"
Provides-Extra: env-docker
Provides-Extra: pydantic
Requires-Dist: pydantic>=2.0.0; extra == "pydantic"
Dynamic: license-file
